{
  "name": "alcoholics/profile_images/+27672123097.jpg",
  "bucket": "alcoholic-expressions.appspot.com",
  "metageneration": 1,
  "generation": 1731172836523,
  "contentType": "image/jpeg",
  "storageClass": "STANDARD",
  "contentDisposition": "inline",
  "downloadTokens": [
    "09759aa6-903a-426d-a680-64e289d42e78"
  ],
  "etag": "BC5BjBfYKSZYi9kuAlsYA9+QuBY",
  "customMetadata": {},
  "timeCreated": "2024-11-09T17:20:36.523Z",
  "updated": "2024-11-09T17:20:36.523Z",
  "size": 18223,
  "md5Hash": "wRDhmf8XUXcAhPIwhL7RIA==",
  "crc32c": "3973683371"
}