{
  "name": "alcoholics/profile_images/+27832674902.jpg",
  "bucket": "alcoholic-expressions.appspot.com",
  "metageneration": 1,
  "generation": 1731172837318,
  "contentType": "image/jpeg",
  "storageClass": "STANDARD",
  "contentDisposition": "inline",
  "downloadTokens": [
    "1e858fe5-ecea-4890-84df-0461ff0f6d9e"
  ],
  "etag": "brsG3F8cX0kfMXhXUIsfe/EQ4Hs",
  "customMetadata": {},
  "timeCreated": "2024-11-09T17:20:37.318Z",
  "updated": "2024-11-09T17:20:37.318Z",
  "size": 16706,
  "md5Hash": "GGmLvakloKW60L/zcpcEBQ==",
  "crc32c": "1898380503"
}