{
  "name": "grand_prices_images/Name-Savana#Qty-6#Vol-330ml.jpg",
  "bucket": "alcoholic-expressions.appspot.com",
  "metageneration": 1,
  "generation": 1729403073006,
  "contentType": "image/jpeg",
  "storageClass": "STANDARD",
  "contentDisposition": "inline",
  "downloadTokens": [
    "eebf9527-d2b2-418b-a172-57a59ab42948"
  ],
  "etag": "22yL8hMyOUmYrrnEegOjIQhsuDk",
  "customMetadata": {},
  "timeCreated": "2024-10-20T05:44:33.006Z",
  "updated": "2024-10-20T05:44:33.006Z",
  "size": 9401,
  "md5Hash": "+vuPTGBoMkgeIZPnvIEgqg==",
  "crc32c": "1002889011"
}